CHA/BlackFrog.py
CHA/CHAF.py
CHA/CommonAlgs.py
CHA/CowCow.py
CHA/CowCowModes.py
CHA/Hashing_Algorithms.py
CHA/KRY.py
CHA/Modes.py
CHA/OAEP.py
CHA/PEMFile.py
CHA/Padding.py
CHA/Piranha.py
CHA/__init__.py
cha_hashing-0.4.8.7.9.dist-info/LICENSE
cha_hashing-0.4.8.7.9.dist-info/METADATA
cha_hashing-0.4.8.7.9.dist-info/WHEEL
cha_hashing-0.4.8.7.9.dist-info/top_level.txt
cha_hashing-0.4.8.7.9.dist-info/RECORD
